cirtap/__init__.py
cirtap/best.py
cirtap/collect.py
cirtap/common.py
cirtap/core.py
cirtap/index.py
cirtap/mailer.py
cirtap/mirror.py
cirtap/pack.py
cirtap-0.3.1.dist-info/AUTHORS.rst
cirtap-0.3.1.dist-info/LICENSE.txt
cirtap-0.3.1.dist-info/METADATA
cirtap-0.3.1.dist-info/WHEEL
cirtap-0.3.1.dist-info/entry_points.txt
cirtap-0.3.1.dist-info/top_level.txt
cirtap-0.3.1.dist-info/RECORD
