Metadata-Version: 2.1
Name: cirtap
Version: 0.3.1
Summary: A CLI to handle PATRIC data from the FTP
Home-page: https://github.com/MGXlab/cirtap/
Author: papanikos
Author-email: nikos.c.pappas@gmail.com
License: MIT
Project-URL: Tracker, https://github.com/MGXlab/cirtap/issues
Project-URL: Documentation, https://github.com/MGXlab/cirtap/wiki
Project-URL: Source, https://github.com/MGXlab/cirtap
Platform: Linux
Classifier: Development Status :: 4 - Beta
Classifier: Programming Language :: Python :: 3
Classifier: Operating System :: POSIX :: Linux
Classifier: Topic :: Scientific/Engineering :: Bio-Informatics
License-File: LICENSE.txt
License-File: AUTHORS.rst
Requires-Dist: pandas (>=1.1.4)
Requires-Dist: biopython
Requires-Dist: click (>=8.0)
Requires-Dist: tqdm
Requires-Dist: ete3
Requires-Dist: importlib-metadata ; python_version < "3.8"
Provides-Extra: testing
Requires-Dist: setuptools ; extra == 'testing'
Requires-Dist: pytest ; extra == 'testing'
Requires-Dist: pytest-cov ; extra == 'testing'
